oacde/__init__.py
oacde/test.py
oacde/algorithms/__init__.py
oacde/algorithms/_algo.py
oacde/algorithms/algoDE.py
oacde/algorithms/algodev.py
oacde/architectures/__init__.py
oacde/architectures/population.py
oacde/operators/DE.py
oacde/operators/DEmat.py
oacde/operators/PSO.py
oacde/operators/__init__.py
oacde/problems/__init__.py
oacde/problems/bbobbenchmarks.py
oacde/problems/problem.py
oacde/publics/__init__.py
oacde/publics/parameterize.py
oacde/publics/tools.py
oacde/tuners/__init__.py
oacde/tuners/_base.py
oacde/tuners/distribution.py
oacde/tuners/multi_armed_bandit.py
oacde/tuners/non_parameter.py
oacde-1.0.2.dist-info/LICENSE
oacde-1.0.2.dist-info/METADATA
oacde-1.0.2.dist-info/WHEEL
oacde-1.0.2.dist-info/top_level.txt
oacde-1.0.2.dist-info/RECORD
