Metadata-Version: 2.1
Name: oacde
Version: 1.0.2
Summary: Online algorithm configuration for differential evolution algorithm (OAC-DE)
Home-page: https://github.com/sustech-opal/oac-de
Author: Changwu Huang, Hao Bai and Xin Yao
Author-email: huangcw3@sustech.edu.cn
Maintainer: Hao Bai
Maintainer-email: hao.bai@insa-rouen.fr
License: Apache License Version 2.0, January 2004
Keywords: Automatic algorithm configuration,Differential evolution algorithm,Adaptive parameter control,Multi-armed bandit,Kernel density estimation,Machine learning
Platform: py38-none-linux_x86_64
Classifier: Programming Language :: Python :: 3 :: Only
Classifier: Topic :: Scientific/Engineering :: Mathematics
Classifier: Intended Audience :: Science/Research
Classifier: License :: Free For Educational Use
Requires-Python: >=3.8
License-File: LICENSE
Requires-Dist: numpy (>=1.17.3)
Requires-Dist: scipy (>=1.2.0)
Requires-Dist: pandas (>=1.3.0)
Requires-Dist: scikit-learn (>=1.0.1)
Requires-Dist: matplotlib (>=2.2.3)
